configbuddy/__init__.py
configbuddy/cli/__init__.py
configbuddy/cli/cli.py
configbuddy/cli/help_formatter.py
configbuddy/core/__init__.py
configbuddy/core/config.py
configbuddy/core/differ.py
configbuddy/core/merger.py
configbuddy/core/types.py
configbuddy/core/validator.py
configbuddy/core/visualizer.py
configbuddy-0.1.0.dist-info/METADATA
configbuddy-0.1.0.dist-info/WHEEL
configbuddy-0.1.0.dist-info/entry_points.txt
configbuddy-0.1.0.dist-info/licenses/LICENSE
configbuddy-0.1.0.dist-info/RECORD
