Metadata-Version: 2.3
Name: configbuddy
Version: 0.1.0
Summary: Configuration file management tool
Author-email: Harim Kang <harimkang4422@gmail.com>
License: MIT
Classifier: Development Status :: 3 - Alpha
Classifier: Intended Audience :: Developers
Classifier: License :: OSI Approved :: MIT License
Classifier: Programming Language :: Python :: 3
Classifier: Programming Language :: Python :: 3.10
Classifier: Programming Language :: Python :: 3.11
Classifier: Programming Language :: Python :: 3.12
Classifier: Topic :: Software Development :: Libraries :: Python Modules
Requires-Python: >=3.10
Requires-Dist: jsonschema>=4.20.0
Requires-Dist: pyyaml>=6.0.1
Requires-Dist: rich-argparse>=1.4.0
Requires-Dist: rich>=13.7.0
Provides-Extra: docs
Requires-Dist: sphinx-autodoc-typehints>=2.5.0; extra == 'docs'
Requires-Dist: sphinx-rtd-theme>=3.0.2; extra == 'docs'
Requires-Dist: sphinx>=8.1.3; extra == 'docs'
Provides-Extra: test
Requires-Dist: pytest-cov>=4.1.0; extra == 'test'
Requires-Dist: pytest>=7.3.1; extra == 'test'
